cfatmos/__about__.py
cfatmos/__init__.py
cfatmos/core.py
cfatmos/data/tabulated_data.bin
cfatmos-0.1.0.dist-info/METADATA
cfatmos-0.1.0.dist-info/WHEEL
cfatmos-0.1.0.dist-info/licenses/LICENSE
cfatmos-0.1.0.dist-info/RECORD
