Metadata-Version: 2.3
Name: cfatmos
Version: 0.1.0
Project-URL: Documentation, https://github.com/nmlucarelli/cfatmos#readme
Project-URL: Issues, https://github.com/nmlucarelli/cfatmos/issues
Project-URL: Source, https://github.com/nmlucarelli/cfatmos
Author-email: Nico Lucarelli <nlucarel@purdue.edu>
License-Expression: MIT
License-File: LICENSE
Classifier: Programming Language :: Python :: 3.10
Classifier: Programming Language :: Python :: 3.11
Classifier: Programming Language :: Python :: 3.12
Requires-Python: >=3.10
Requires-Dist: numpy>=1.20.0
Requires-Dist: pandas>=1.0.0
Requires-Dist: typing>=3.7.4
